django_regexfield-0.0.0a0.dist-info/DESCRIPTION.rst
django_regexfield-0.0.0a0.dist-info/LICENSE.txt
django_regexfield-0.0.0a0.dist-info/METADATA
django_regexfield-0.0.0a0.dist-info/RECORD
django_regexfield-0.0.0a0.dist-info/WHEEL
django_regexfield-0.0.0a0.dist-info/metadata.json
django_regexfield-0.0.0a0.dist-info/top_level.txt
regexfield/__init__.py
tests/__init__.py
tests/settings.py
tests/tests.py
